podcast_transformer/__init__.py
podcast_transformer/cli.py
podcast_transformer-0.1.2.dist-info/METADATA
podcast_transformer-0.1.2.dist-info/WHEEL
podcast_transformer-0.1.2.dist-info/entry_points.txt
podcast_transformer-0.1.2.dist-info/top_level.txt
podcast_transformer-0.1.2.dist-info/RECORD
