Metadata-Version: 2.4
Name: podcast-transformer
Version: 0.1.2
Summary: CLI 工具：下载并增强 YouTube 播客字幕，支持 Azure OpenAI 转写与总结
Author: Lee
License: Proprietary
Requires-Python: >=3.10
Requires-Dist: openai>=1.30.0
Requires-Dist: youtube-transcript-api>=0.6.2
Requires-Dist: yt-dlp>=2024.3.10
Requires-Dist: httpx[socks]>=0.27.0
Provides-Extra: dev
Requires-Dist: pytest>=8.0.0; extra == "dev"
